nfuid.py
nfuid-2.0.6.dist-info/METADATA
nfuid-2.0.6.dist-info/WHEEL
nfuid-2.0.6.dist-info/top_level.txt
nfuid-2.0.6.dist-info/RECORD
