Metadata-Version: 2.4
Name: nfuid
Version: 2.0.6
Summary: Minimal 11-character URL-safe unique ID generator with hidden mode and timestamp-based structure.
Home-page: https://github.com/niefdev/nfuid
Author: niefdev
Author-email: niefdev@gmail.com
Project-URL: Bug Reports, https://github.com/niefdev/nfuid/issues
Project-URL: Source, https://github.com/niefdev/nfuid
Keywords: id unique-id short-id uuid identifier base64 timestamp url-safe nfuid
Classifier: Development Status :: 5 - Production/Stable
Classifier: Intended Audience :: Developers
Classifier: License :: OSI Approved :: MIT License
Classifier: Operating System :: OS Independent
Classifier: Programming Language :: Python :: 3
Classifier: Programming Language :: Python :: 3.6
Classifier: Programming Language :: Python :: 3.7
Classifier: Programming Language :: Python :: 3.8
Classifier: Programming Language :: Python :: 3.9
Classifier: Programming Language :: Python :: 3.10
Requires-Python: >=3.6
Dynamic: author
Dynamic: author-email
Dynamic: classifier
Dynamic: description
Dynamic: description-content-type
Dynamic: home-page
Dynamic: keywords
Dynamic: project-url
Dynamic: requires-python
Dynamic: summary
